LICENSE
MANIFEST.in
README.md
pyproject.toml
requirements.txt
setup.py
filling/__init__.py
filling/check_constraint_evaluator.py
filling/column_mappings_generator.py
filling/data_generator.py
filling/helpers.py
intelligent_data_generator.egg-info/PKG-INFO
intelligent_data_generator.egg-info/SOURCES.txt
intelligent_data_generator.egg-info/dependency_links.txt
intelligent_data_generator.egg-info/requires.txt
intelligent_data_generator.egg-info/top_level.txt
parsing/__init__.py
parsing/parsing.py
tests/__init__.py
tests/test_complex_db.py
tests/test_complex_db_v2.py
tests/test_employees_data_generation.py
tests/test_library_data_generation.py
tests/test_serial_unsigned_bigint_PKs.py
tests/test_theater_data_generation.py