Metadata-Version: 2.1
Name: intelligent-data-generator
Version: 1.2.3
Summary: A Python package for generating semantically and syntactically correct data for RDBMS.
Home-page: https://github.com/Kamil-Krawiec/Data-filler.git
Author: Kamil Krawiec
Author-email: kamil.krawiec9977@gmail.com
Classifier: Programming Language :: Python :: 3
Classifier: License :: OSI Approved :: MIT License
Classifier: Operating System :: OS Independent
Requires-Python: >=3.10
License-File: LICENSE
